monkey/__init__.py
monkey/main.py
deploy_monkey-0.0.4.dist-info/METADATA
deploy_monkey-0.0.4.dist-info/WHEEL
deploy_monkey-0.0.4.dist-info/top_level.txt
deploy_monkey-0.0.4.dist-info/RECORD
