Metadata-Version: 2.1
Name: deploy-monkey
Version: 0.0.4
Summary: Currently to prevent dependency-confusion. Aim to open source later
Author-email: Tino de Bruijn <tino@solarmonkey.nl>
Classifier: Programming Language :: Python :: 3
Classifier: License :: OSI Approved :: MIT License
Classifier: Operating System :: OS Independent
